LICENSE
README.md
setup.py
django_radius.egg-info/PKG-INFO
django_radius.egg-info/SOURCES.txt
django_radius.egg-info/dependency_links.txt
django_radius.egg-info/not-zip-safe
django_radius.egg-info/requires.txt
django_radius.egg-info/top_level.txt
radiusauth/__init__.py
radiusauth/backends/__init__.py
radiusauth/backends/radius.py