Metadata-Version: 2.1
Name: django-radius
Version: 1.5.1
Summary: Django authentication backend for RADIUS
Home-page: http://robgolding63.github.com/django-radius/
Author: Rob Golding
Author-email: rob@robgolding.com
License: BSD
Classifier: Programming Language :: Python
Classifier: Programming Language :: Python :: 3
Classifier: Framework :: Django
Classifier: Intended Audience :: Developers
Classifier: Operating System :: OS Independent
License-File: LICENSE
